gcscanner/__init__.py
gcscanner/bucket_manager.py
gcscanner/check.py
gcscanner/colors.py
gcscanner/logger.py
gcscanner/main.py
gcscanner/output.py
gcscanner/parser.py
gcscanner/project_manager.py
gcscanner/scope.py
gcscanner/utils.py
GCScanner-0.2.5.dist-info/LICENSE
GCScanner-0.2.5.dist-info/METADATA
GCScanner-0.2.5.dist-info/WHEEL
GCScanner-0.2.5.dist-info/entry_points.txt
GCScanner-0.2.5.dist-info/top_level.txt
GCScanner-0.2.5.dist-info/RECORD
