Metadata-Version: 2.1
Name: GCScanner
Version: 0.2.5
Summary: GCScanner list buckets with details and show where are the public data in your GCP account
Author-email: Jeremie Robert <appydo@gmail.com>
License: Copyright (C) 2022 Jeremie Robert <appydo@gmail.com>
Project-URL: Homepage, https://github.com/jerob/GCScanner
Project-URL: documentation, https://github.com/jerob/GCScanner/blob/main/README.md
Project-URL: Bug Tracker, https://github.com/jerob/GCScanner/issues
Classifier: Programming Language :: Python :: 3
Classifier: License :: OSI Approved :: MIT License
Classifier: Operating System :: OS Independent
Requires-Python: >=3.7
License-File: LICENSE
Requires-Dist: google-cloud-storage
Requires-Dist: google-cloud-resource-manager
Requires-Dist: termcolor
Requires-Dist: print2
Provides-Extra: dev
Requires-Dist: black ; extra == 'dev'
Requires-Dist: flake8 ; extra == 'dev'
Requires-Dist: pytest ; extra == 'dev'
